.DS_Store
demesstify/__init__.py
demesstify/emojis.py
demesstify/errors.py
demesstify/parse.py
demesstify/parser.py
demesstify/reactions.py
demesstify/analysis/__init__.py
demesstify/analysis/attachments.py
demesstify/analysis/emojis.py
demesstify/analysis/reactions.py
demesstify/analysis/sentiment.py
demesstify/analysis/text.py
demesstify/clean/__init__.py
demesstify/clean/clean.py
demesstify/database/__init__.py
demesstify/database/chat.py
demesstify/testing/__init__.py
demesstify/testing/messages.py
demesstify/testing/settings.py
demesstify/visualize/__init__.py
demesstify/visualize/cloud.py
demesstify/visualize/color_funcs.py
demesstify/visualize/plots.py
demesstify-2.2.0.dist-info/METADATA
demesstify-2.2.0.dist-info/WHEEL
demesstify-2.2.0.dist-info/top_level.txt
demesstify-2.2.0.dist-info/RECORD
