Metadata-Version: 2.1
Name: demesstify
Version: 2.2.0
Summary: 📱Demystifies your messages and allows for easy analysis and visualization of conversations.
Author: Jake Brehm
Author-email: <mail@jakebrehm.com>
Classifier: Development Status :: 3 - Alpha
Classifier: Intended Audience :: Developers
Classifier: Programming Language :: Python :: 3
Classifier: Operating System :: MacOS :: MacOS X
Requires-Dist: pandas
Requires-Dist: matplotlib
Requires-Dist: wordcloud
Requires-Dist: emoji
Requires-Dist: lorem
Requires-Dist: vaderSentiment
Requires-Dist: calmap
